{
  "posts": [
    {
      "id": "1",
      "title": "블로그 이동!111112",
      "body": "블로그 이동! TEST!213123123sdfsdfsdfsdf211212212",
      "publish": true,
      "createdAt": 1720527288052
    },
    {
      "id": "2",
      "title": "블로그 이동!",
      "body": "블로그 이동! TEST!",
      "publish": false,
      "createdAt": 1720525449120
    },
    {
      "id": "3",
      "title": "블로그 이동!",
      "body": "블로그 이동! TEST!",
      "publish": true,
      "createdAt": 1720525449130
    },
    {
      "id": "4",
      "title": "블로그 이동!",
      "body": "블로그 이동! TEST!",
      "publish": false,
      "createdAt": 1720525441000
    },
    {
      "id": "d964",
      "title": "test!@",
      "body": "test!@~~~",
      "publish": true,
      "createdAt": 1720525449946
    },
    {
      "id": "5b22",
      "title": "dfsdfsfsdf",
      "body": "sdfsdfsdfsdf",
      "publish": true,
      "createdAt": 1720529123476
    }
  ]
}